LICENSE
MANIFEST.in
README.md
setup.py
pydi/__init__.py
pydi/container.py
pydi/exceptions.py
pydi/utils.py
pydi.egg-info/PKG-INFO
pydi.egg-info/SOURCES.txt
pydi.egg-info/dependency_links.txt
pydi.egg-info/top_level.txt