Metadata-Version: 1.0
Name: pydi
Version: 0.3.1
Summary: Little Dependency Injection Container
Home-page: http://github.com/aventurella/pydi
Author: Adam Venturella
Author-email: aventurella@gmail.com
License: Copyright (c) 2012 Adam Venturella.
